uscisstatus/__init__.py
uscisstatus-0.1.1.dist-info/DESCRIPTION.rst
uscisstatus-0.1.1.dist-info/METADATA
uscisstatus-0.1.1.dist-info/RECORD
uscisstatus-0.1.1.dist-info/WHEEL
uscisstatus-0.1.1.dist-info/metadata.json
uscisstatus-0.1.1.dist-info/top_level.txt
