Metadata-Version: 2.0
Name: uscisstatus
Version: 0.1.1
Summary: USCIS Status Checker
Home-page: http://github.com/meauxt/uscisstatus
Author: Mohamad Tarbin
Author-email: mhed.t91@gmail.com
License: MIT
Platform: UNKNOWN
Requires-Dist: lxml
Requires-Dist: requests
